{
	"info": {
		"_postman_id": "d58b011e-924a-4e23-a50a-46c36fab0b71",
		"name": "API Facturación SUNAT - Configuración Completa",
		"description": "Colección completa para configurar y usar la API de Facturación Electrónica SUNAT desde cero. Incluye todos los endpoints necesarios para emitir comprobantes electrónicos.",
		"schema": "https://schema.getpostman.com/json/collection/v2.1.0/collection.json",
		"_exporter_id": "20633485"
	},
	"item": [
		{
			"name": "🔧 1. SETUP Y MIGRACIONES",
			"item": [
				{
					"name": "1.1 - Ejecutar Migraciones",
					"request": {
						"method": "POST",
						"header": [
							{
								"key": "Accept",
								"value": "application/json"
							}
						],
						"url": {
							"raw": "{{base_url}}/setup/migrate",
							"host": ["{{base_url}}"],
							"path": ["setup", "migrate"]
						}
					},
					"response": []
				},
				{
					"name": "1.2 - Ejecutar Seeders",
					"request": {
						"method": "POST",
						"header": [
							{
								"key": "Accept",
								"value": "application/json"
							}
						],
						"url": {
							"raw": "{{base_url}}/setup/seed",
							"host": ["{{base_url}}"],
							"path": ["setup", "seed"]
						}
					},
					"response": []
				},
				{
					"name": "1.3 - Verificar Estado del Sistema",
					"request": {
						"method": "GET",
						"header": [
							{
								"key": "Accept",
								"value": "application/json"
							}
						],
						"url": {
							"raw": "{{base_url}}/setup/status",
							"host": ["{{base_url}}"],
							"path": ["setup", "status"]
						}
					},
					"response": []
				}
			]
		},
		{
			"name": "🚀 2. CONFIGURACIÓN INICIAL DEL SISTEMA",
			"item": [
				{
					"name": "2.1 - Información del Sistema",
					"request": {
						"method": "GET",
						"header": [
							{
								"key": "Accept",
								"value": "application/json"
							}
						],
						"url": {
							"raw": "{{base_url}}/system/info",
							"host": ["{{base_url}}"],
							"path": ["system", "info"]
						}
					},
					"response": []
				},
				{
					"name": "2.2 - Inicializar Sistema (Solo primera vez)",
					"request": {
						"method": "POST",
						"header": [
							{
								"key": "Content-Type",
								"value": "application/json"
							},
							{
								"key": "Accept",
								"value": "application/json"
							}
						],
						"body": {
							"mode": "raw",
							"raw": "{\n  \"name\": \"Administrador\",\n  \"email\": \"admin@empresa.com\",\n  \"password\": \"Admin123\",\n  \"password_confirmation\": \"Admin123\"\n}"
						},
						"url": {
							"raw": "{{base_url}}/auth/initialize",
							"host": ["{{base_url}}"],
							"path": ["auth", "initialize"]
						}
					},
					"response": []
				},
				{
					"name": "2.3 - Login y Obtener Token",
					"event": [
						{
							"listen": "test",
							"script": {
								"exec": [
									"if (pm.response.code === 200) {",
									"    var jsonData = pm.response.json();",
									"    pm.collectionVariables.set('access_token', jsonData.data.access_token);",
									"    console.log('Token guardado: ' + jsonData.data.access_token);",
									"}"
								],
								"type": "text/javascript"
							}
						}
					],
					"request": {
						"method": "POST",
						"header": [
							{
								"key": "Content-Type",
								"value": "application/json"
							},
							{
								"key": "Accept",
								"value": "application/json"
							}
						],
						"body": {
							"mode": "raw",
							"raw": "{\n  \"email\": \"admin@empresa.com\",\n  \"password\": \"Admin123\"\n}"
						},
						"url": {
							"raw": "{{base_url}}/auth/login",
							"host": ["{{base_url}}"],
							"path": ["auth", "login"]
						}
					},
					"response": []
				}
			]
		},
		{
			"name": "🏢 3. CONFIGURACIÓN DE EMPRESA",
			"item": [
				{
					"name": "3.1 - Setup Completo de Empresa (CON ARCHIVOS)",
					"event": [
						{
							"listen": "test",
							"script": {
								"exec": [
									"if (pm.response.code === 200) {",
									"    var jsonData = pm.response.json();",
									"    if (jsonData.company && jsonData.company.id) {",
									"        pm.collectionVariables.set('company_id', jsonData.company.id);",
									"        console.log('Company ID guardado: ' + jsonData.company.id);",
									"    }",
									"    if (jsonData.branch && jsonData.branch.id) {",
									"        pm.collectionVariables.set('branch_id', jsonData.branch.id);",
									"        console.log('Branch ID guardado: ' + jsonData.branch.id);",
									"    }",
									"}"
								],
								"type": "text/javascript"
							}
						}
					],
					"request": {
						"method": "POST",
						"header": [
							{
								"key": "Authorization",
								"value": "Bearer {{access_token}}"
							}
						],
						"body": {
							"mode": "formdata",
							"formdata": [
								{
									"key": "environment",
									"value": "beta",
									"type": "text"
								},
								{
									"key": "company[ruc]",
									"value": "20123456789",
									"type": "text"
								},
								{
									"key": "company[razon_social]",
									"value": "EMPRESA DE PRUEBA S.A.C.",
									"type": "text"
								},
								{
									"key": "company[nombre_comercial]",
									"value": "Empresa Prueba",
									"type": "text"
								},
								{
									"key": "company[direccion]",
									"value": "Av. Los Olivos 123, Miraflores",
									"type": "text"
								},
								{
									"key": "company[ubigeo]",
									"value": "150101",
									"type": "text"
								},
								{
									"key": "company[distrito]",
									"value": "Miraflores",
									"type": "text"
								},
								{
									"key": "company[provincia]",
									"value": "Lima",
									"type": "text"
								},
								{
									"key": "company[departamento]",
									"value": "Lima",
									"type": "text"
								},
								{
									"key": "company[telefono]",
									"value": "01-1234567",
									"type": "text"
								},
								{
									"key": "company[email]",
									"value": "contacto@empresa.com",
									"type": "text"
								},
								{
									"key": "company[web]",
									"value": "https://www.empresa.com",
									"type": "text"
								},
								{
									"key": "company[usuario_sol]",
									"value": "MODDATOS",
									"type": "text"
								},
								{
									"key": "company[clave_sol]",
									"value": "moddatos",
									"type": "text"
								},
								{
									"key": "certificado_pem",
									"description": "Archivo .pem del certificado digital",
									"type": "file",
									"src": []
								},
								{
									"key": "certificado_password",
									"value": "password_certificado",
									"type": "text"
								},
								{
									"key": "logo_path",
									"type": "file",
									"src": []
								},
								{
									"key": "modo_produccion",
									"value": "false",
									"type": "text"
								},
								{
									"key": "activo",
									"value": "true",
									"type": "text"
								}
							]
						},
						"url": {
							"raw": "{{base_url}}/v1/setup/complete",
							"host": ["{{base_url}}"],
							"path": ["v1", "setup", "complete"]
						}
					},
					"response": []
				},
				{
					"name": "3.2 - Listar Empresas",
					"request": {
						"method": "GET",
						"header": [
							{
								"key": "Authorization",
								"value": "Bearer {{access_token}}"
							},
							{
								"key": "Accept",
								"value": "application/json"
							}
						],
						"url": {
							"raw": "{{base_url}}/v1/companies",
							"host": ["{{base_url}}"],
							"path": ["v1", "companies"]
						}
					},
					"response": []
				},
				{
					"name": "3.3 - Ver Empresa Específica",
					"request": {
						"method": "GET",
						"header": [
							{
								"key": "Authorization",
								"value": "Bearer {{access_token}}"
							},
							{
								"key": "Accept",
								"value": "application/json"
							}
						],
						"url": {
							"raw": "{{base_url}}/v1/companies/{{company_id}}",
							"host": ["{{base_url}}"],
							"path": ["v1", "companies", "{{company_id}}"]
						}
					},
					"response": []
				}
			]
		},
		{
			"name": "🏪 4. CONFIGURACIÓN DE SUCURSALES",
			"item": [
				{
					"name": "4.1 - Listar Sucursales por Empresa",
					"request": {
						"method": "GET",
						"header": [
							{
								"key": "Authorization",
								"value": "Bearer {{access_token}}"
							},
							{
								"key": "Accept",
								"value": "application/json"
							}
						],
						"url": {
							"raw": "{{base_url}}/v1/companies/{{company_id}}/branches",
							"host": ["{{base_url}}"],
							"path": ["v1", "companies", "{{company_id}}", "branches"]
						}
					},
					"response": []
				},
				{
					"name": "4.2 - Crear Nueva Sucursal",
					"request": {
						"method": "POST",
						"header": [
							{
								"key": "Authorization",
								"value": "Bearer {{access_token}}"
							},
							{
								"key": "Content-Type",
								"value": "application/json"
							},
							{
								"key": "Accept",
								"value": "application/json"
							}
						],
						"body": {
							"mode": "raw",
							"raw": "{\n  \"company_id\": {{company_id}},\n  \"codigo\": \"0001\",\n  \"nombre\": \"Sucursal San Isidro\",\n  \"direccion\": \"Av. Javier Prado 456\",\n  \"ubigeo\": \"150101\",\n  \"distrito\": \"San Isidro\",\n  \"provincia\": \"Lima\",\n  \"departamento\": \"Lima\",\n  \"activo\": true\n}"
						},
						"url": {
							"raw": "{{base_url}}/v1/branches",
							"host": ["{{base_url}}"],
							"path": ["v1", "branches"]
						}
					},
					"response": []
				}
			]
		},
		{
			"name": "👥 5. GESTIÓN DE CLIENTES",
			"item": [
				{
					"name": "5.1 - Crear Cliente",
					"event": [
						{
							"listen": "test",
							"script": {
								"type": "text/javascript",
								"exec": [
									"if (pm.response.code === 201) {",
									"    var jsonData = pm.response.json();",
									"    if (jsonData.data && jsonData.data.id) {",
									"        pm.collectionVariables.set('client_id', jsonData.data.id);",
									"        console.log('Client ID guardado: ' + jsonData.data.id);",
									"    }",
									"}"
								]
							}
						}
					],
					"request": {
						"method": "POST",
						"header": [
							{
								"key": "Authorization",
								"value": "Bearer {{access_token}}"
							},
							{
								"key": "Content-Type",
								"value": "application/json"
							},
							{
								"key": "Accept",
								"value": "application/json"
							}
						],
						"body": {
							"mode": "raw",
							"raw": "{\n  \"company_id\": {{company_id}},\n  \"tipo_documento\": \"1\",\n  \"numero_documento\": \"12345678\",\n  \"razon_social\": \"CLIENTE PRUEBA S.A.C.\",\n  \"nombre_comercial\": \"Cliente Prueba\",\n  \"direccion\": \"Jr. Los Sauces 789\",\n  \"ubigeo\": \"150101\",\n  \"distrito\": \"Lima\",\n  \"provincia\": \"Lima\",\n  \"departamento\": \"Lima\",\n  \"telefono\": \"01-9876543\",\n  \"email\": \"cliente@email.com\"\n}"
						},
						"url": {
							"raw": "{{base_url}}/v1/clients",
							"host": ["{{base_url}}"],
							"path": ["v1", "clients"]
						}
					},
					"response": []
				},
				{
					"name": "5.2 - Buscar Cliente por Documento",
					"request": {
						"method": "POST",
						"header": [
							{
								"key": "Authorization",
								"value": "Bearer {{access_token}}"
							},
							{
								"key": "Content-Type",
								"value": "application/json"
							},
							{
								"key": "Accept",
								"value": "application/json"
							}
						],
						"body": {
							"mode": "raw",
							"raw": "{\n  \"company_id\": {{company_id}},\n  \"tipo_documento\": \"1\",\n  \"numero_documento\": \"12345678\"\n}"
						},
						"url": {
							"raw": "{{base_url}}/v1/clients/search-by-document",
							"host": ["{{base_url}}"],
							"path": ["v1", "clients", "search-by-document"]
						}
					},
					"response": []
				},
				{
					"name": "5.3 - Listar Clientes por Empresa",
					"request": {
						"method": "GET",
						"header": [
							{
								"key": "Authorization",
								"value": "Bearer {{access_token}}"
							},
							{
								"key": "Accept",
								"value": "application/json"
							}
						],
						"url": {
							"raw": "{{base_url}}/v1/companies/{{company_id}}/clients",
							"host": ["{{base_url}}"],
							"path": ["v1", "companies", "{{company_id}}", "clients"]
						}
					},
					"response": []
				}
			]
		},
		{
			"name": "🔢 6. CONFIGURACIÓN DE CORRELATIVOS",
			"item": [
				{
					"name": "6.1 - Ver Correlativos de Sucursal",
					"request": {
						"method": "GET",
						"header": [
							{
								"key": "Authorization",
								"value": "Bearer {{access_token}}"
							},
							{
								"key": "Accept",
								"value": "application/json"
							}
						],
						"url": {
							"raw": "{{base_url}}/v1/branches/{{branch_id}}/correlatives",
							"host": ["{{base_url}}"],
							"path": ["v1", "branches", "{{branch_id}}", "correlatives"]
						}
					},
					"response": []
				},
				{
					"name": "6.2 - Crear Correlativos Básicos en Lote",
					"request": {
						"method": "POST",
						"header": [
							{
								"key": "Authorization",
								"value": "Bearer {{access_token}}"
							},
							{
								"key": "Content-Type",
								"value": "application/json"
							},
							{
								"key": "Accept",
								"value": "application/json"
							}
						],
						"body": {
							"mode": "raw",
							"raw": "{\n  \"correlativos\": [\n    {\n      \"tipo_documento\": \"01\",\n      \"serie\": \"F001\",\n      \"numero\": 1,\n      \"descripcion\": \"Facturas\"\n    },\n    {\n      \"tipo_documento\": \"03\",\n      \"serie\": \"B001\",\n      \"numero\": 1,\n      \"descripcion\": \"Boletas\"\n    },\n    {\n      \"tipo_documento\": \"07\",\n      \"serie\": \"FC01\",\n      \"numero\": 1,\n      \"descripcion\": \"Notas de Crédito\"\n    },\n    {\n      \"tipo_documento\": \"08\",\n      \"serie\": \"FD01\",\n      \"numero\": 1,\n      \"descripcion\": \"Notas de Débito\"\n    },\n    {\n      \"tipo_documento\": \"09\",\n      \"serie\": \"T001\",\n      \"numero\": 1,\n      \"descripcion\": \"Guías de Remisión\"\n    }\n  ]\n}"
						},
						"url": {
							"raw": "{{base_url}}/v1/branches/{{branch_id}}/correlatives/batch",
							"host": ["{{base_url}}"],
							"path": ["v1", "branches", "{{branch_id}}", "correlatives", "batch"]
						}
					},
					"response": []
				},
				{
					"name": "6.3 - Ver Tipos de Documentos Disponibles",
					"request": {
						"method": "GET",
						"header": [
							{
								"key": "Authorization",
								"value": "Bearer {{access_token}}"
							},
							{
								"key": "Accept",
								"value": "application/json"
							}
						],
						"url": {
							"raw": "{{base_url}}/v1/correlatives/document-types",
							"host": ["{{base_url}}"],
							"path": ["v1", "correlatives", "document-types"]
						}
					},
					"response": []
				}
			]
		},
		{
			"name": "🧾 7. EMISIÓN DE DOCUMENTOS ELECTRÓNICOS",
			"item": [
				{
					"name": "7.1 - Crear Factura (Básica)",
					"event": [
						{
							"listen": "test",
							"script": {
								"type": "text/javascript",
								"exec": [
									"if (pm.response.code === 201) {",
									"    var jsonData = pm.response.json();",
									"    if (jsonData.data && jsonData.data.id) {",
									"        pm.collectionVariables.set('invoice_id', jsonData.data.id);",
									"        console.log('Invoice ID guardado: ' + jsonData.data.id);",
									"    }",
									"}"
								]
							}
						}
					],
					"request": {
						"method": "POST",
						"header": [
							{
								"key": "Authorization",
								"value": "Bearer {{access_token}}"
							},
							{
								"key": "Content-Type",
								"value": "application/json"
							},
							{
								"key": "Accept",
								"value": "application/json"
							}
						],
						"body": {
							"mode": "raw",
							"raw": "{\n  \"company_id\": {{company_id}},\n  \"branch_id\": {{branch_id}},\n  \"serie\": \"F001\",\n  \"fecha_emision\": \"2025-09-11\",\n  \"moneda\": \"PEN\",\n  \"forma_pago_tipo\": \"Contado\",\n  \"client\": {\n    \"tipo_documento\": \"6\",\n    \"numero_documento\": \"20123456789\",\n    \"razon_social\": \"EMPRESA CLIENTE SAC\",\n    \"direccion\": \"Av. Principal 123\",\n    \"email\": \"cliente@email.com\"\n  },\n  \"detalles\": [\n    {\n      \"codigo\": \"P001\",\n      \"descripcion\": \"Producto de ejemplo\",\n      \"unidad\": \"NIU\",\n      \"cantidad\": 2,\n      \"mto_valor_unitario\": 100.00,\n      \"tip_afe_igv\": \"10\"\n    }\n  ]\n}"
						},
						"url": {
							"raw": "{{base_url}}/v1/invoices",
							"host": ["{{base_url}}"],
							"path": ["v1", "invoices"]
						}
					},
					"response": []
				},
				{
					"name": "7.2 - Crear Factura (Con Detracción)",
					"request": {
						"method": "POST",
						"header": [
							{
								"key": "Authorization",
								"value": "Bearer {{access_token}}"
							},
							{
								"key": "Content-Type",
								"value": "application/json"
							},
							{
								"key": "Accept",
								"value": "application/json"
							}
						],
						"body": {
							"mode": "raw",
							"raw": "{\n  \"company_id\": {{company_id}},\n  \"branch_id\": {{branch_id}},\n  \"serie\": \"F001\",\n  \"fecha_emision\": \"2025-09-11\",\n  \"moneda\": \"PEN\",\n  \"forma_pago_tipo\": \"Contado\",\n  \"client\": {\n    \"tipo_documento\": \"6\",\n    \"numero_documento\": \"20123456789\",\n    \"razon_social\": \"EMPRESA CLIENTE SAC\",\n    \"direccion\": \"Av. Principal 123\",\n    \"email\": \"cliente@email.com\"\n  },\n  \"detalles\": [\n    {\n      \"codigo\": \"SERV001\",\n      \"descripcion\": \"Servicio de Consultoría\",\n      \"unidad\": \"ZZ\",\n      \"cantidad\": 1,\n      \"mto_valor_unitario\": 1000.00,\n      \"tip_afe_igv\": \"10\"\n    }\n  ],\n  \"detraccion\": {\n    \"codigo_bien_servicio\": \"001\",\n    \"porcentaje\": 10.0\n  }\n}"
						},
						"url": {
							"raw": "{{base_url}}/v1/invoices",
							"host": ["{{base_url}}"],
							"path": ["v1", "invoices"]
						}
					},
					"response": []
				},
				{
					"name": "7.3 - Crear Factura (Al Crédito)",
					"request": {
						"method": "POST",
						"header": [
							{
								"key": "Authorization",
								"value": "Bearer {{access_token}}"
							},
							{
								"key": "Content-Type",
								"value": "application/json"
							},
							{
								"key": "Accept",
								"value": "application/json"
							}
						],
						"body": {
							"mode": "raw",
							"raw": "{\n  \"company_id\": {{company_id}},\n  \"branch_id\": {{branch_id}},\n  \"serie\": \"F001\",\n  \"fecha_emision\": \"2025-09-11\",\n  \"fecha_vencimiento\": \"2025-10-11\",\n  \"moneda\": \"PEN\",\n  \"forma_pago_tipo\": \"Credito\",\n  \"forma_pago_cuotas\": [\n    {\n      \"moneda\": \"PEN\",\n      \"monto\": 236.00,\n      \"fecha_pago\": \"2025-10-11\"\n    }\n  ],\n  \"client\": {\n    \"tipo_documento\": \"6\",\n    \"numero_documento\": \"20123456789\",\n    \"razon_social\": \"EMPRESA CLIENTE SAC\",\n    \"direccion\": \"Av. Principal 123\",\n    \"email\": \"cliente@email.com\"\n  },\n  \"detalles\": [\n    {\n      \"codigo\": \"P002\",\n      \"descripcion\": \"Producto al crédito\",\n      \"unidad\": \"NIU\",\n      \"cantidad\": 2,\n      \"mto_valor_unitario\": 100.00,\n      \"tip_afe_igv\": \"10\"\n    }\n  ]\n}"
						},
						"url": {
							"raw": "{{base_url}}/v1/invoices",
							"host": ["{{base_url}}"],
							"path": ["v1", "invoices"]
						}
					},
					"response": []
				},
				{
					"name": "7.4 - Crear Boleta",
					"event": [
						{
							"listen": "test",
							"script": {
								"type": "text/javascript",
								"exec": [
									"if (pm.response.code === 201) {",
									"    var jsonData = pm.response.json();",
									"    if (jsonData.data && jsonData.data.id) {",
									"        pm.collectionVariables.set('boleta_id', jsonData.data.id);",
									"        console.log('Boleta ID guardado: ' + jsonData.data.id);",
									"    }",
									"}"
								]
							}
						}
					],
					"request": {
						"method": "POST",
						"header": [
							{
								"key": "Authorization",
								"value": "Bearer {{access_token}}"
							},
							{
								"key": "Content-Type",
								"value": "application/json"
							},
							{
								"key": "Accept",
								"value": "application/json"
							}
						],
						"body": {
							"mode": "raw",
							"raw": "{\n  \"company_id\": {{company_id}},\n  \"branch_id\": {{branch_id}},\n  \"serie\": \"B001\",\n  \"fecha_emision\": \"2025-09-11\",\n  \"moneda\": \"PEN\",\n  \"forma_pago_tipo\": \"Contado\",\n  \"client\": {\n    \"tipo_documento\": \"1\",\n    \"numero_documento\": \"12345678\",\n    \"razon_social\": \"CLIENTE PERSONA NATURAL\"\n  },\n  \"detalles\": [\n    {\n      \"codigo\": \"SERV001\",\n      \"descripcion\": \"Servicio de Consultoría\",\n      \"unidad\": \"ZZ\",\n      \"cantidad\": 1,\n      \"mto_valor_unitario\": 200.00,\n      \"tip_afe_igv\": \"10\"\n    }\n  ]\n}"
						},
						"url": {
							"raw": "{{base_url}}/v1/boletas",
							"host": ["{{base_url}}"],
							"path": ["v1", "boletas"]
						}
					},
					"response": []
				},
				{
					"name": "7.5 - Crear Nota de Crédito",
					"event": [
						{
							"listen": "test",
							"script": {
								"type": "text/javascript",
								"exec": [
									"if (pm.response.code === 201) {",
									"    var jsonData = pm.response.json();",
									"    if (jsonData.data && jsonData.data.id) {",
									"        pm.collectionVariables.set('credit_note_id', jsonData.data.id);",
									"        console.log('Credit Note ID guardado: ' + jsonData.data.id);",
									"    }",
									"}"
								]
							}
						}
					],
					"request": {
						"method": "POST",
						"header": [
							{
								"key": "Authorization",
								"value": "Bearer {{access_token}}"
							},
							{
								"key": "Content-Type",
								"value": "application/json"
							},
							{
								"key": "Accept",
								"value": "application/json"
							}
						],
						"body": {
							"mode": "raw",
							"raw": "{\n  \"company_id\": {{company_id}},\n  \"branch_id\": {{branch_id}},\n  \"serie\": \"FC01\",\n  \"fecha_emision\": \"2025-09-11\",\n  \"moneda\": \"PEN\",\n  \"cod_motivo\": \"01\",\n  \"des_motivo\": \"Anulación de la operación\",\n  \"client\": {\n    \"tipo_documento\": \"6\",\n    \"numero_documento\": \"20123456789\",\n    \"razon_social\": \"EMPRESA CLIENTE SAC\"\n  },\n  \"documento_relacionado\": {\n    \"tipo_documento\": \"01\",\n    \"serie_numero\": \"F001-1\"\n  },\n  \"detalles\": [\n    {\n      \"codigo\": \"P001\",\n      \"descripcion\": \"Producto de ejemplo\",\n      \"unidad\": \"NIU\",\n      \"cantidad\": 1,\n      \"mto_valor_unitario\": 100.00,\n      \"tip_afe_igv\": \"10\"\n    }\n  ]\n}"
						},
						"url": {
							"raw": "{{base_url}}/v1/credit-notes",
							"host": ["{{base_url}}"],
							"path": ["v1", "credit-notes"]
						}
					},
					"response": []
				},
				{
					"name": "7.6 - Crear Nota de Débito",
					"event": [
						{
							"listen": "test",
							"script": {
								"type": "text/javascript",
								"exec": [
									"if (pm.response.code === 201) {",
									"    var jsonData = pm.response.json();",
									"    if (jsonData.data && jsonData.data.id) {",
									"        pm.collectionVariables.set('debit_note_id', jsonData.data.id);",
									"        console.log('Debit Note ID guardado: ' + jsonData.data.id);",
									"    }",
									"}"
								]
							}
						}
					],
					"request": {
						"method": "POST",
						"header": [
							{
								"key": "Authorization",
								"value": "Bearer {{access_token}}"
							},
							{
								"key": "Content-Type",
								"value": "application/json"
							},
							{
								"key": "Accept",
								"value": "application/json"
							}
						],
						"body": {
							"mode": "raw",
							"raw": "{\n  \"company_id\": {{company_id}},\n  \"branch_id\": {{branch_id}},\n  \"serie\": \"FD01\",\n  \"fecha_emision\": \"2025-09-11\",\n  \"moneda\": \"PEN\",\n  \"cod_motivo\": \"01\",\n  \"des_motivo\": \"Intereses por mora\",\n  \"client\": {\n    \"tipo_documento\": \"6\",\n    \"numero_documento\": \"20123456789\",\n    \"razon_social\": \"EMPRESA CLIENTE SAC\"\n  },\n  \"documento_relacionado\": {\n    \"tipo_documento\": \"01\",\n    \"serie_numero\": \"F001-1\"\n  },\n  \"detalles\": [\n    {\n      \"codigo\": \"INT001\",\n      \"descripcion\": \"Intereses por pago tardío\",\n      \"unidad\": \"ZZ\",\n      \"cantidad\": 1,\n      \"mto_valor_unitario\": 50.00,\n      \"tip_afe_igv\": \"10\"\n    }\n  ]\n}"
						},
						"url": {
							"raw": "{{base_url}}/v1/debit-notes",
							"host": ["{{base_url}}"],
							"path": ["v1", "debit-notes"]
						}
					},
					"response": []
				}
			]
		},
		{
			"name": "📤 8. ENVÍO A SUNAT",
			"item": [
				{
					"name": "8.1 - Listar Facturas",
					"request": {
						"method": "GET",
						"header": [
							{
								"key": "Authorization",
								"value": "Bearer {{access_token}}"
							},
							{
								"key": "Accept",
								"value": "application/json"
							}
						],
						"url": {
							"raw": "{{base_url}}/v1/invoices?company_id={{company_id}}",
							"host": ["{{base_url}}"],
							"path": ["v1", "invoices"],
							"query": [
								{
									"key": "company_id",
									"value": "{{company_id}}"
								}
							]
						}
					},
					"response": []
				},
				{
					"name": "8.2 - Enviar Factura a SUNAT",
					"request": {
						"method": "POST",
						"header": [
							{
								"key": "Authorization",
								"value": "Bearer {{access_token}}"
							},
							{
								"key": "Accept",
								"value": "application/json"
							}
						],
						"url": {
							"raw": "{{base_url}}/v1/invoices/{{invoice_id}}/send-sunat",
							"host": ["{{base_url}}"],
							"path": ["v1", "invoices", "{{invoice_id}}", "send-sunat"]
						}
					},
					"response": []
				},
				{
					"name": "8.3 - Listar Boletas Pendientes de Resumen",
					"request": {
						"method": "GET",
						"header": [
							{
								"key": "Authorization",
								"value": "Bearer {{access_token}}"
							},
							{
								"key": "Accept",
								"value": "application/json"
							}
						],
						"url": {
							"raw": "{{base_url}}/v1/boletas/pending-for-summary?company_id={{company_id}}",
							"host": ["{{base_url}}"],
							"path": ["v1", "boletas", "pending-for-summary"],
							"query": [
								{
									"key": "company_id",
									"value": "{{company_id}}"
								}
							]
						}
					},
					"response": []
				},
				{
					"name": "8.4 - Crear Resumen Diario de Boletas",
					"request": {
						"method": "POST",
						"header": [
							{
								"key": "Authorization",
								"value": "Bearer {{access_token}}"
							},
							{
								"key": "Content-Type",
								"value": "application/json"
							},
							{
								"key": "Accept",
								"value": "application/json"
							}
						],
						"body": {
							"mode": "raw",
							"raw": "{\n  \"company_id\": {{company_id}},\n  \"branch_id\": {{branch_id}},\n  \"fecha_resumen\": \"2025-09-11\"\n}"
						},
						"url": {
							"raw": "{{base_url}}/v1/boletas/create-daily-summary",
							"host": ["{{base_url}}"],
							"path": ["v1", "boletas", "create-daily-summary"]
						}
					},
					"response": []
				},
				{
					"name": "8.5 - Enviar Nota de Crédito a SUNAT",
					"request": {
						"method": "POST",
						"header": [
							{
								"key": "Authorization",
								"value": "Bearer {{access_token}}"
							},
							{
								"key": "Accept",
								"value": "application/json"
							}
						],
						"url": {
							"raw": "{{base_url}}/v1/credit-notes/{{credit_note_id}}/send-sunat",
							"host": ["{{base_url}}"],
							"path": ["v1", "credit-notes", "{{credit_note_id}}", "send-sunat"]
						}
					},
					"response": []
				},
				{
					"name": "8.6 - Enviar Nota de Débito a SUNAT",
					"request": {
						"method": "POST",
						"header": [
							{
								"key": "Authorization",
								"value": "Bearer {{access_token}}"
							},
							{
								"key": "Accept",
								"value": "application/json"
							}
						],
						"url": {
							"raw": "{{base_url}}/v1/debit-notes/{{debit_note_id}}/send-sunat",
							"host": ["{{base_url}}"],
							"path": ["v1", "debit-notes", "{{debit_note_id}}", "send-sunat"]
						}
					},
					"response": []
				}
			]
		},
		{
			"name": "📄 9. DESCARGA DE ARCHIVOS",
			"item": [
				{
					"name": "9.1 - Generar PDF de Factura",
					"request": {
						"method": "POST",
						"header": [
							{
								"key": "Authorization",
								"value": "Bearer {{access_token}}"
							},
							{
								"key": "Content-Type",
								"value": "application/json"
							},
							{
								"key": "Accept",
								"value": "application/json"
							}
						],
						"body": {
							"mode": "raw",
							"raw": "{\n  \"formato\": \"a4\",\n  \"template\": \"default\"\n}"
						},
						"url": {
							"raw": "{{base_url}}/v1/invoices/{{invoice_id}}/generate-pdf",
							"host": ["{{base_url}}"],
							"path": ["v1", "invoices", "{{invoice_id}}", "generate-pdf"]
						}
					},
					"response": []
				},
				{
					"name": "9.2 - Descargar XML de Factura",
					"request": {
						"method": "GET",
						"header": [
							{
								"key": "Authorization",
								"value": "Bearer {{access_token}}"
							}
						],
						"url": {
							"raw": "{{base_url}}/v1/invoices/{{invoice_id}}/download-xml",
							"host": ["{{base_url}}"],
							"path": ["v1", "invoices", "{{invoice_id}}", "download-xml"]
						}
					},
					"response": []
				},
				{
					"name": "9.3 - Descargar CDR de Factura",
					"request": {
						"method": "GET",
						"header": [
							{
								"key": "Authorization",
								"value": "Bearer {{access_token}}"
							}
						],
						"url": {
							"raw": "{{base_url}}/v1/invoices/{{invoice_id}}/download-cdr",
							"host": ["{{base_url}}"],
							"path": ["v1", "invoices", "{{invoice_id}}", "download-cdr"]
						}
					},
					"response": []
				},
				{
					"name": "9.4 - Descargar PDF de Factura",
					"request": {
						"method": "GET",
						"header": [
							{
								"key": "Authorization",
								"value": "Bearer {{access_token}}"
							}
						],
						"url": {
							"raw": "{{base_url}}/v1/invoices/{{invoice_id}}/download-pdf",
							"host": ["{{base_url}}"],
							"path": ["v1", "invoices", "{{invoice_id}}", "download-pdf"]
						}
					},
					"response": []
				}
			]
		},
		{
			"name": "🚚 10. GUÍAS DE REMISIÓN",
			"item": [
				{
					"name": "10.1 - Crear Guía de Remisión (Transporte Público)",
					"event": [
						{
							"listen": "test",
							"script": {
								"type": "text/javascript",
								"exec": [
									"if (pm.response.code === 201) {",
									"    var jsonData = pm.response.json();",
									"    if (jsonData.data && jsonData.data.id) {",
									"        pm.collectionVariables.set('dispatch_guide_id', jsonData.data.id);",
									"        console.log('Dispatch Guide ID guardado: ' + jsonData.data.id);",
									"    }",
									"}"
								]
							}
						}
					],
					"request": {
						"method": "POST",
						"header": [
							{
								"key": "Authorization",
								"value": "Bearer {{access_token}}"
							},
							{
								"key": "Content-Type",
								"value": "application/json"
							},
							{
								"key": "Accept",
								"value": "application/json"
							}
						],
						"body": {
							"mode": "raw",
							"raw": "{\n  \"company_id\": {{company_id}},\n  \"branch_id\": {{branch_id}},\n  \"destinatario_id\": {{client_id}},\n  \"serie\": \"T001\",\n  \"fecha_emision\": \"2025-09-11\",\n  \"fecha_traslado\": \"2025-09-12\",\n  \"version\": \"2022\",\n  \"cod_traslado\": \"01\",\n  \"des_traslado\": \"Venta\",\n  \"mod_traslado\": \"01\",\n  \"peso_total\": 15.5,\n  \"und_peso_total\": \"KGM\",\n  \"num_bultos\": 2,\n  \"partida_ubigeo\": \"150101\",\n  \"partida_direccion\": \"Av. Los Olivos 123, Miraflores\",\n  \"partida_ruc\": \"20123456789\",\n  \"partida_cod_local\": \"0001\",\n  \"llegada_ubigeo\": \"150114\",\n  \"llegada_direccion\": \"Jr. Las Flores 456, San Borja\",\n  \"llegada_ruc\": \"12345678\",\n  \"transportista_tipo_doc\": \"6\",\n  \"transportista_num_doc\": \"20987654321\",\n  \"transportista_razon_social\": \"TRANSPORTES LIMA S.A.C.\",\n  \"transportista_nro_mtc\": \"MTC123456\",\n  \"detalles\": [\n    {\n      \"cantidad\": 10,\n      \"unidad\": \"NIU\",\n      \"descripcion\": \"Producto A\",\n      \"codigo\": \"PROD001\",\n      \"peso_total\": 10.0\n    },\n    {\n      \"cantidad\": 5,\n      \"unidad\": \"NIU\",\n      \"descripcion\": \"Producto B\",\n      \"codigo\": \"PROD002\",\n      \"peso_total\": 5.5\n    }\n  ],\n  \"observaciones\": \"Guía de remisión de prueba con transporte público\",\n  \"usuario_creacion\": \"admin\"\n}"
						},
						"url": {
							"raw": "{{base_url}}/v1/dispatch-guides",
							"host": ["{{base_url}}"],
							"path": ["v1", "dispatch-guides"]
						}
					},
					"response": []
				},
				{
					"name": "10.2 - Crear Guía de Remisión (Transporte Privado)",
					"request": {
						"method": "POST",
						"header": [
							{
								"key": "Authorization",
								"value": "Bearer {{access_token}}"
							},
							{
								"key": "Content-Type",
								"value": "application/json"
							},
							{
								"key": "Accept",
								"value": "application/json"
							}
						],
						"body": {
							"mode": "raw",
							"raw": "{\n  \"company_id\": {{company_id}},\n  \"branch_id\": {{branch_id}},\n  \"destinatario_id\": {{client_id}},\n  \"serie\": \"T001\",\n  \"fecha_emision\": \"2025-09-11\",\n  \"fecha_traslado\": \"2025-09-12\",\n  \"version\": \"2022\",\n  \"cod_traslado\": \"04\",\n  \"des_traslado\": \"Traslado entre establecimientos de la misma empresa\",\n  \"mod_traslado\": \"02\",\n  \"peso_total\": 25.0,\n  \"und_peso_total\": \"KGM\",\n  \"num_bultos\": 3,\n  \"partida_ubigeo\": \"150101\",\n  \"partida_direccion\": \"Av. Los Olivos 123, Miraflores\",\n  \"partida_ruc\": \"20123456789\",\n  \"partida_cod_local\": \"0001\",\n  \"llegada_ubigeo\": \"150114\",\n  \"llegada_direccion\": \"Jr. Las Flores 456, San Borja\",\n  \"llegada_ruc\": \"20123456789\",\n  \"llegada_cod_local\": \"0002\",\n  \"conductor_tipo\": \"Principal\",\n  \"conductor_tipo_doc\": \"1\",\n  \"conductor_num_doc\": \"12345678\",\n  \"conductor_licencia\": \"A12345678\",\n  \"conductor_nombres\": \"Juan Carlos\",\n  \"conductor_apellidos\": \"Pérez García\",\n  \"vehiculo_placa\": \"ABC-123\",\n  \"vehiculos_secundarios\": [\n    {\n      \"placa\": \"DEF-456\"\n    }\n  ],\n  \"detalles\": [\n    {\n      \"cantidad\": 20,\n      \"unidad\": \"NIU\",\n      \"descripcion\": \"Materiales de oficina\",\n      \"codigo\": \"MAT001\",\n      \"peso_total\": 15.0\n    },\n    {\n      \"cantidad\": 10,\n      \"unidad\": \"KGM\",\n      \"descripcion\": \"Suministros varios\",\n      \"codigo\": \"SUM001\",\n      \"peso_total\": 10.0\n    }\n  ],\n  \"observaciones\": \"Traslado entre sucursales - Transporte privado\",\n  \"usuario_creacion\": \"admin\"\n}"
						},
						"url": {
							"raw": "{{base_url}}/v1/dispatch-guides",
							"host": ["{{base_url}}"],
							"path": ["v1", "dispatch-guides"]
						}
					},
					"response": []
				},
				{
					"name": "10.3 - Listar Guías de Remisión",
					"request": {
						"method": "GET",
						"header": [
							{
								"key": "Authorization",
								"value": "Bearer {{access_token}}"
							},
							{
								"key": "Accept",
								"value": "application/json"
							}
						],
						"url": {
							"raw": "{{base_url}}/v1/dispatch-guides?company_id={{company_id}}&per_page=20",
							"host": ["{{base_url}}"],
							"path": ["v1", "dispatch-guides"],
							"query": [
								{
									"key": "company_id",
									"value": "{{company_id}}"
								},
								{
									"key": "per_page",
									"value": "20"
								}
							]
						}
					},
					"response": []
				},
				{
					"name": "10.4 - Enviar Guía a SUNAT",
					"request": {
						"method": "POST",
						"header": [
							{
								"key": "Authorization",
								"value": "Bearer {{access_token}}"
							},
							{
								"key": "Accept",
								"value": "application/json"
							}
						],
						"url": {
							"raw": "{{base_url}}/v1/dispatch-guides/{{dispatch_guide_id}}/send-sunat",
							"host": ["{{base_url}}"],
							"path": ["v1", "dispatch-guides", "{{dispatch_guide_id}}", "send-sunat"]
						}
					},
					"response": []
				},
				{
					"name": "10.5 - Obtener Motivos de Traslado",
					"request": {
						"method": "GET",
						"header": [
							{
								"key": "Authorization",
								"value": "Bearer {{access_token}}"
							},
							{
								"key": "Accept",
								"value": "application/json"
							}
						],
						"url": {
							"raw": "{{base_url}}/v1/dispatch-guides/catalogs/transfer-reasons",
							"host": ["{{base_url}}"],
							"path": ["v1", "dispatch-guides", "catalogs", "transfer-reasons"]
						}
					},
					"response": []
				},
				{
					"name": "10.6 - Crear Guía M1L (Vehículos Menores)",
					"request": {
						"method": "POST",
						"header": [
							{
								"key": "Authorization",
								"value": "Bearer {{access_token}}"
							},
							{
								"key": "Content-Type",
								"value": "application/json"
							},
							{
								"key": "Accept",
								"value": "application/json"
							}
						],
						"body": {
							"mode": "raw",
							"raw": "{\n  \"company_id\": {{company_id}},\n  \"branch_id\": {{branch_id}},\n  \"destinatario_id\": {{client_id}},\n  \"serie\": \"T001\",\n  \"fecha_emision\": \"2025-09-11\",\n  \"fecha_traslado\": \"2025-09-11\",\n  \"version\": \"2022\",\n  \"cod_traslado\": \"01\",\n  \"des_traslado\": \"Venta\",\n  \"mod_traslado\": \"02\",\n  \"peso_total\": 5.0,\n  \"und_peso_total\": \"KGM\",\n  \"num_bultos\": 1,\n  \"partida_ubigeo\": \"150101\",\n  \"partida_direccion\": \"Av. Los Olivos 123, Miraflores\",\n  \"partida_ruc\": \"20123456789\",\n  \"partida_cod_local\": \"0001\",\n  \"llegada_ubigeo\": \"150114\",\n  \"llegada_direccion\": \"Jr. Las Flores 456, San Borja\",\n  \"llegada_ruc\": \"12345678\",\n  \"indicadores\": [\n    \"SUNAT_Envio_IndicadorTrasladoVehiculoM1L\"\n  ],\n  \"detalles\": [\n    {\n      \"cantidad\": 2,\n      \"unidad\": \"NIU\",\n      \"descripcion\": \"Producto liviano para entrega en vehículo menor\",\n      \"codigo\": \"LIGHT001\",\n      \"peso_total\": 5.0\n    }\n  ],\n  \"observaciones\": \"Entrega con vehículo menor M1L\",\n  \"usuario_creacion\": \"admin\"\n}"
						},
						"url": {
							"raw": "{{base_url}}/v1/dispatch-guides",
							"host": ["{{base_url}}"],
							"path": ["v1", "dispatch-guides"]
						}
					},
					"response": []
				},
				{
					"name": "10.7 - Crear Guía de Exportación",
					"request": {
						"method": "POST",
						"header": [
							{
								"key": "Authorization",
								"value": "Bearer {{access_token}}"
							},
							{
								"key": "Content-Type",
								"value": "application/json"
							},
							{
								"key": "Accept",
								"value": "application/json"
							}
						],
						"body": {
							"mode": "raw",
							"raw": "{\n  \"company_id\": {{company_id}},\n  \"branch_id\": {{branch_id}},\n  \"destinatario_id\": {{client_id}},\n  \"serie\": \"T001\",\n  \"fecha_emision\": \"2025-09-11\",\n  \"fecha_traslado\": \"2025-09-12\",\n  \"version\": \"2022\",\n  \"cod_traslado\": \"13\",\n  \"des_traslado\": \"Exportación\",\n  \"mod_traslado\": \"01\",\n  \"peso_total\": 100.0,\n  \"und_peso_total\": \"KGM\",\n  \"num_bultos\": 5,\n  \"partida_ubigeo\": \"150101\",\n  \"partida_direccion\": \"Av. Los Olivos 123, Miraflores\",\n  \"partida_ruc\": \"20123456789\",\n  \"partida_cod_local\": \"0001\",\n  \"llegada_ubigeo\": \"071301\",\n  \"llegada_direccion\": \"Puerto del Callao\",\n  \"llegada_ruc\": \"20123456789\",\n  \"llegada_cod_local\": \"PUERTO\",\n  \"transportista_tipo_doc\": \"6\",\n  \"transportista_num_doc\": \"20555666777\",\n  \"transportista_razon_social\": \"TRANSPORTES EXPORTACIÓN S.A.C.\",\n  \"transportista_nro_mtc\": \"MTC789456\",\n  \"detalles\": [\n    {\n      \"cantidad\": 50,\n      \"unidad\": \"NIU\",\n      \"descripcion\": \"Productos para exportación\",\n      \"codigo\": \"EXP001\",\n      \"peso_total\": 100.0\n    }\n  ],\n  \"observaciones\": \"Guía para exportación - Puerto del Callao\",\n  \"usuario_creacion\": \"admin\"\n}"
						},
						"url": {
							"raw": "{{base_url}}/v1/dispatch-guides",
							"host": ["{{base_url}}"],
							"path": ["v1", "dispatch-guides"]
						}
					},
					"response": []
				},
				{
					"name": "10.8 - Crear Guía de Importación",
					"request": {
						"method": "POST",
						"header": [
							{
								"key": "Authorization",
								"value": "Bearer {{access_token}}"
							},
							{
								"key": "Content-Type",
								"value": "application/json"
							},
							{
								"key": "Accept",
								"value": "application/json"
							}
						],
						"body": {
							"mode": "raw",
							"raw": "{\n  \"company_id\": {{company_id}},\n  \"branch_id\": {{branch_id}},\n  \"destinatario_id\": {{client_id}},\n  \"serie\": \"T001\",\n  \"fecha_emision\": \"2025-09-11\",\n  \"fecha_traslado\": \"2025-09-12\",\n  \"version\": \"2022\",\n  \"cod_traslado\": \"08\",\n  \"des_traslado\": \"Importación\",\n  \"mod_traslado\": \"01\",\n  \"peso_total\": 200.0,\n  \"und_peso_total\": \"KGM\",\n  \"num_bultos\": 10,\n  \"partida_ubigeo\": \"071301\",\n  \"partida_direccion\": \"Puerto del Callao\",\n  \"partida_ruc\": \"20123456789\",\n  \"partida_cod_local\": \"PUERTO\",\n  \"llegada_ubigeo\": \"150101\",\n  \"llegada_direccion\": \"Av. Los Olivos 123, Miraflores\",\n  \"llegada_ruc\": \"20123456789\",\n  \"llegada_cod_local\": \"0001\",\n  \"transportista_tipo_doc\": \"6\",\n  \"transportista_num_doc\": \"20444555666\",\n  \"transportista_razon_social\": \"TRANSPORTES IMPORTACIÓN S.A.C.\",\n  \"transportista_nro_mtc\": \"MTC654321\",\n  \"detalles\": [\n    {\n      \"cantidad\": 100,\n      \"unidad\": \"NIU\",\n      \"descripcion\": \"Productos importados\",\n      \"codigo\": \"IMP001\",\n      \"peso_total\": 200.0\n    }\n  ],\n  \"observaciones\": \"Guía para importación desde puerto\",\n  \"usuario_creacion\": \"admin\"\n}"
						},
						"url": {
							"raw": "{{base_url}}/v1/dispatch-guides",
							"host": ["{{base_url}}"],
							"path": ["v1", "dispatch-guides"]
						}
					},
					"response": []
				},
				{
					"name": "10.9 - Crear Guía con Vehículos Secundarios",
					"request": {
						"method": "POST",
						"header": [
							{
								"key": "Authorization",
								"value": "Bearer {{access_token}}"
							},
							{
								"key": "Content-Type",
								"value": "application/json"
							},
							{
								"key": "Accept",
								"value": "application/json"
							}
						],
						"body": {
							"mode": "raw",
							"raw": "{\n  \"company_id\": {{company_id}},\n  \"branch_id\": {{branch_id}},\n  \"destinatario_id\": {{client_id}},\n  \"serie\": \"T001\",\n  \"fecha_emision\": \"2025-09-11\",\n  \"fecha_traslado\": \"2025-09-12\",\n  \"version\": \"2022\",\n  \"cod_traslado\": \"01\",\n  \"des_traslado\": \"Venta\",\n  \"mod_traslado\": \"02\",\n  \"peso_total\": 500.0,\n  \"und_peso_total\": \"KGM\",\n  \"num_bultos\": 20,\n  \"partida_ubigeo\": \"150101\",\n  \"partida_direccion\": \"Av. Los Olivos 123, Miraflores\",\n  \"partida_ruc\": \"20123456789\",\n  \"partida_cod_local\": \"0001\",\n  \"llegada_ubigeo\": \"040101\",\n  \"llegada_direccion\": \"Av. Bolognesi 500, Arequipa\",\n  \"llegada_ruc\": \"20777888999\",\n  \"llegada_cod_local\": \"AQP001\",\n  \"conductor_tipo\": \"Principal\",\n  \"conductor_tipo_doc\": \"1\",\n  \"conductor_num_doc\": \"87654321\",\n  \"conductor_licencia\": \"B87654321\",\n  \"conductor_nombres\": \"Carlos Alberto\",\n  \"conductor_apellidos\": \"Rodríguez Vega\",\n  \"vehiculo_placa\": \"XYZ-789\",\n  \"vehiculos_secundarios\": [\n    {\n      \"placa\": \"ABC-456\"\n    },\n    {\n      \"placa\": \"DEF-123\"\n    }\n  ],\n  \"detalles\": [\n    {\n      \"cantidad\": 100,\n      \"unidad\": \"NIU\",\n      \"descripcion\": \"Productos pesados para Arequipa\",\n      \"codigo\": \"HEAVY001\",\n      \"peso_total\": 300.0\n    },\n    {\n      \"cantidad\": 50,\n      \"unidad\": \"NIU\",\n      \"descripcion\": \"Materiales complementarios\",\n      \"codigo\": \"HEAVY002\",\n      \"peso_total\": 200.0\n    }\n  ],\n  \"observaciones\": \"Traslado con vehículos secundarios a Arequipa\",\n  \"usuario_creacion\": \"admin\"\n}"
						},
						"url": {
							"raw": "{{base_url}}/v1/dispatch-guides",
							"host": ["{{base_url}}"],
							"path": ["v1", "dispatch-guides"]
						}
					},
					"response": []
				},
				{
					"name": "10.10 - Ver Guía de Remisión Específica",
					"request": {
						"method": "GET",
						"header": [
							{
								"key": "Authorization",
								"value": "Bearer {{access_token}}"
							},
							{
								"key": "Accept",
								"value": "application/json"
							}
						],
						"url": {
							"raw": "{{base_url}}/v1/dispatch-guides/{{dispatch_guide_id}}",
							"host": ["{{base_url}}"],
							"path": ["v1", "dispatch-guides", "{{dispatch_guide_id}}"]
						}
					},
					"response": []
				},
				{
					"name": "10.11 - Verificar Estado de Guía en SUNAT",
					"request": {
						"method": "POST",
						"header": [
							{
								"key": "Authorization",
								"value": "Bearer {{access_token}}"
							},
							{
								"key": "Accept",
								"value": "application/json"
							}
						],
						"url": {
							"raw": "{{base_url}}/v1/dispatch-guides/{{dispatch_guide_id}}/check-status",
							"host": ["{{base_url}}"],
							"path": ["v1", "dispatch-guides", "{{dispatch_guide_id}}", "check-status"]
						}
					},
					"response": []
				},
				{
					"name": "10.12 - Generar PDF de Guía",
					"request": {
						"method": "POST",
						"header": [
							{
								"key": "Authorization",
								"value": "Bearer {{access_token}}"
							},
							{
								"key": "Content-Type",
								"value": "application/json"
							},
							{
								"key": "Accept",
								"value": "application/json"
							}
						],
						"body": {
							"mode": "raw",
							"raw": "{\n  \"formato\": \"a4\",\n  \"template\": \"default\"\n}"
						},
						"url": {
							"raw": "{{base_url}}/v1/dispatch-guides/{{dispatch_guide_id}}/generate-pdf",
							"host": ["{{base_url}}"],
							"path": ["v1", "dispatch-guides", "{{dispatch_guide_id}}", "generate-pdf"]
						}
					},
					"response": []
				},
				{
					"name": "10.13 - Descargar XML de Guía",
					"request": {
						"method": "GET",
						"header": [
							{
								"key": "Authorization",
								"value": "Bearer {{access_token}}"
							}
						],
						"url": {
							"raw": "{{base_url}}/v1/dispatch-guides/{{dispatch_guide_id}}/download-xml",
							"host": ["{{base_url}}"],
							"path": ["v1", "dispatch-guides", "{{dispatch_guide_id}}", "download-xml"]
						}
					},
					"response": []
				},
				{
					"name": "10.14 - Descargar CDR de Guía",
					"request": {
						"method": "GET",
						"header": [
							{
								"key": "Authorization",
								"value": "Bearer {{access_token}}"
							}
						],
						"url": {
							"raw": "{{base_url}}/v1/dispatch-guides/{{dispatch_guide_id}}/download-cdr",
							"host": ["{{base_url}}"],
							"path": ["v1", "dispatch-guides", "{{dispatch_guide_id}}", "download-cdr"]
						}
					},
					"response": []
				},
				{
					"name": "10.15 - Descargar PDF de Guía",
					"request": {
						"method": "GET",
						"header": [
							{
								"key": "Authorization",
								"value": "Bearer {{access_token}}"
							}
						],
						"url": {
							"raw": "{{base_url}}/v1/dispatch-guides/{{dispatch_guide_id}}/download-pdf",
							"host": ["{{base_url}}"],
							"path": ["v1", "dispatch-guides", "{{dispatch_guide_id}}", "download-pdf"]
						}
					},
					"response": []
				},
				{
					"name": "10.16 - Obtener Motivos de Traslado",
					"request": {
						"method": "GET",
						"header": [
							{
								"key": "Authorization",
								"value": "Bearer {{access_token}}"
							},
							{
								"key": "Accept",
								"value": "application/json"
							}
						],
						"url": {
							"raw": "{{base_url}}/v1/dispatch-guides/catalogs/transfer-reasons",
							"host": ["{{base_url}}"],
							"path": ["v1", "dispatch-guides", "catalogs", "transfer-reasons"]
						}
					},
					"response": []
				},
				{
					"name": "10.17 - Obtener Modalidades de Transporte",
					"request": {
						"method": "GET",
						"header": [
							{
								"key": "Authorization",
								"value": "Bearer {{access_token}}"
							},
							{
								"key": "Accept",
								"value": "application/json"
							}
						],
						"url": {
							"raw": "{{base_url}}/v1/dispatch-guides/catalogs/transport-modes",
							"host": ["{{base_url}}"],
							"path": ["v1", "dispatch-guides", "catalogs", "transport-modes"]
						}
					},
					"response": []
				}
			]
		},
		{
			"name": "📋 11. CATÁLOGOS Y UBIGEOS",
			"item": [
				{
					"name": "11.1 - Listar Regiones",
					"request": {
						"method": "GET",
						"header": [
							{
								"key": "Authorization",
								"value": "Bearer {{access_token}}"
							},
							{
								"key": "Accept",
								"value": "application/json"
							}
						],
						"url": {
							"raw": "{{base_url}}/v1/ubigeos/regiones",
							"host": ["{{base_url}}"],
							"path": ["v1", "ubigeos", "regiones"]
						}
					},
					"response": []
				},
				{
					"name": "11.2 - Listar Provincias de Lima",
					"request": {
						"method": "GET",
						"header": [
							{
								"key": "Authorization",
								"value": "Bearer {{access_token}}"
							},
							{
								"key": "Accept",
								"value": "application/json"
							}
						],
						"url": {
							"raw": "{{base_url}}/v1/ubigeos/provincias?region_id=15",
							"host": ["{{base_url}}"],
							"path": ["v1", "ubigeos", "provincias"],
							"query": [
								{
									"key": "region_id",
									"value": "15"
								}
							]
						}
					},
					"response": []
				},
				{
					"name": "11.3 - Listar Distritos de Lima",
					"request": {
						"method": "GET",
						"header": [
							{
								"key": "Authorization",
								"value": "Bearer {{access_token}}"
							},
							{
								"key": "Accept",
								"value": "application/json"
							}
						],
						"url": {
							"raw": "{{base_url}}/v1/ubigeos/distritos?provincia_id=1501",
							"host": ["{{base_url}}"],
							"path": ["v1", "ubigeos", "distritos"],
							"query": [
								{
									"key": "provincia_id",
									"value": "1501"
								}
							]
						}
					},
					"response": []
				},
				{
					"name": "11.4 - Buscar Ubigeo",
					"request": {
						"method": "GET",
						"header": [
							{
								"key": "Authorization",
								"value": "Bearer {{access_token}}"
							},
							{
								"key": "Accept",
								"value": "application/json"
							}
						],
						"url": {
							"raw": "{{base_url}}/v1/ubigeos/search?q=lima&tipo=distrito",
							"host": ["{{base_url}}"],
							"path": ["v1", "ubigeos", "search"],
							"query": [
								{
									"key": "q",
									"value": "lima"
								},
								{
									"key": "tipo",
									"value": "distrito"
								}
							]
						}
					},
					"response": []
				},
				{
					"name": "11.5 - Obtener Formatos PDF Disponibles",
					"request": {
						"method": "GET",
						"header": [
							{
								"key": "Authorization",
								"value": "Bearer {{access_token}}"
							},
							{
								"key": "Accept",
								"value": "application/json"
							}
						],
						"url": {
							"raw": "{{base_url}}/v1/pdf/formats",
							"host": ["{{base_url}}"],
							"path": ["v1", "pdf", "formats"]
						}
					},
					"response": []
				},
				{
					"name": "11.6 - Obtener Motivos de Nota de Crédito",
					"request": {
						"method": "GET",
						"header": [
							{
								"key": "Authorization",
								"value": "Bearer {{access_token}}"
							},
							{
								"key": "Accept",
								"value": "application/json"
							}
						],
						"url": {
							"raw": "{{base_url}}/v1/credit-notes/catalogs/motivos",
							"host": ["{{base_url}}"],
							"path": ["v1", "credit-notes", "catalogs", "motivos"]
						}
					},
					"response": []
				},
				{
					"name": "11.7 - Obtener Motivos de Nota de Débito",
					"request": {
						"method": "GET",
						"header": [
							{
								"key": "Authorization",
								"value": "Bearer {{access_token}}"
							},
							{
								"key": "Accept",
								"value": "application/json"
							}
						],
						"url": {
							"raw": "{{base_url}}/v1/debit-notes/catalogs/motivos",
							"host": ["{{base_url}}"],
							"path": ["v1", "debit-notes", "catalogs", "motivos"]
						}
					},
					"response": []
				}
			]
		},
		{
			"name": "⚙️ 12. CONFIGURACIONES AVANZADAS Y GRE",
			"item": [
				{
					"name": "12.1 - Ver Configuración Completa de Empresa",
					"request": {
						"method": "GET",
						"header": [
							{
								"key": "Authorization",
								"value": "Bearer {{access_token}}"
							},
							{
								"key": "Accept",
								"value": "application/json"
							}
						],
						"url": {
							"raw": "{{base_url}}/v1/companies/{{company_id}}/config",
							"host": ["{{base_url}}"],
							"path": ["v1", "companies", "{{company_id}}", "config"]
						}
					},
					"response": []
				},
				{
					"name": "12.2 - Validar Servicios SUNAT",
					"request": {
						"method": "GET",
						"header": [
							{
								"key": "Authorization",
								"value": "Bearer {{access_token}}"
							},
							{
								"key": "Accept",
								"value": "application/json"
							}
						],
						"url": {
							"raw": "{{base_url}}/v1/companies/{{company_id}}/config/validate/services",
							"host": ["{{base_url}}"],
							"path": ["v1", "companies", "{{company_id}}", "config", "validate", "services"]
						}
					},
					"response": []
				},
				{
					"name": "12.3 - Ver Credenciales GRE Actuales",
					"request": {
						"method": "GET",
						"header": [
							{
								"key": "Authorization",
								"value": "Bearer {{access_token}}"
							},
							{
								"key": "Accept",
								"value": "application/json"
							}
						],
						"url": {
							"raw": "{{base_url}}/v1/companies/{{company_id}}/gre-credentials",
							"host": ["{{base_url}}"],
							"path": ["v1", "companies", "{{company_id}}", "gre-credentials"]
						}
					},
					"response": []
				},
				{
					"name": "12.4 - Configurar Credenciales GRE (BETA)",
					"request": {
						"method": "PUT",
						"header": [
							{
								"key": "Authorization",
								"value": "Bearer {{access_token}}"
							},
							{
								"key": "Content-Type",
								"value": "application/json"
							},
							{
								"key": "Accept",
								"value": "application/json"
							}
						],
						"body": {
							"mode": "raw",
							"raw": "{\n  \"environment\": \"beta\",\n  \"client_id\": \"test-85e5b0ae-255c-4891-a595-0b98c65c9854\",\n  \"client_secret\": \"test-Hty/M6QshYvPgItX2P0+Kw==\",\n  \"ruc_proveedor\": \"20161515648\",\n  \"usuario_sol\": \"MODDATOS\",\n  \"clave_sol\": \"moddatos\"\n}"
						},
						"url": {
							"raw": "{{base_url}}/v1/companies/{{company_id}}/gre-credentials",
							"host": ["{{base_url}}"],
							"path": ["v1", "companies", "{{company_id}}", "gre-credentials"]
						}
					},
					"response": []
				},
				{
					"name": "12.5 - Configurar Credenciales GRE (PRODUCCIÓN)",
					"request": {
						"method": "PUT",
						"header": [
							{
								"key": "Authorization",
								"value": "Bearer {{access_token}}"
							},
							{
								"key": "Content-Type",
								"value": "application/json"
							},
							{
								"key": "Accept",
								"value": "application/json"
							}
						],
						"body": {
							"mode": "raw",
							"raw": "{\n  \"environment\": \"produccion\",\n  \"client_id\": \"TU_CLIENT_ID_PRODUCCION\",\n  \"client_secret\": \"TU_CLIENT_SECRET_PRODUCCION\",\n  \"ruc_proveedor\": \"20123456789\",\n  \"usuario_sol\": \"TU_USUARIO_SOL\",\n  \"clave_sol\": \"TU_CLAVE_SOL\"\n}"
						},
						"url": {
							"raw": "{{base_url}}/v1/companies/{{company_id}}/gre-credentials",
							"host": ["{{base_url}}"],
							"path": ["v1", "companies", "{{company_id}}", "gre-credentials"]
						}
					},
					"response": []
				},
				{
					"name": "12.6 - Probar Conexión GRE (BETA)",
					"request": {
						"method": "POST",
						"header": [
							{
								"key": "Authorization",
								"value": "Bearer {{access_token}}"
							},
							{
								"key": "Content-Type",
								"value": "application/json"
							},
							{
								"key": "Accept",
								"value": "application/json"
							}
						],
						"body": {
							"mode": "raw",
							"raw": "{\n  \"environment\": \"beta\"\n}"
						},
						"url": {
							"raw": "{{base_url}}/v1/companies/{{company_id}}/gre-credentials/test-connection",
							"host": ["{{base_url}}"],
							"path": ["v1", "companies", "{{company_id}}", "gre-credentials", "test-connection"]
						}
					},
					"response": []
				},
				{
					"name": "12.7 - Probar Conexión GRE (PRODUCCIÓN)",
					"request": {
						"method": "POST",
						"header": [
							{
								"key": "Authorization",
								"value": "Bearer {{access_token}}"
							},
							{
								"key": "Content-Type",
								"value": "application/json"
							},
							{
								"key": "Accept",
								"value": "application/json"
							}
						],
						"body": {
							"mode": "raw",
							"raw": "{\n  \"environment\": \"produccion\"\n}"
						},
						"url": {
							"raw": "{{base_url}}/v1/companies/{{company_id}}/gre-credentials/test-connection",
							"host": ["{{base_url}}"],
							"path": ["v1", "companies", "{{company_id}}", "gre-credentials", "test-connection"]
						}
					},
					"response": []
				},
				{
					"name": "12.8 - Copiar Credenciales GRE Entre Empresas",
					"request": {
						"method": "POST",
						"header": [
							{
								"key": "Authorization",
								"value": "Bearer {{access_token}}"
							},
							{
								"key": "Content-Type",
								"value": "application/json"
							},
							{
								"key": "Accept",
								"value": "application/json"
							}
						],
						"body": {
							"mode": "raw",
							"raw": "{\n  \"source_company_id\": {{company_id}},\n  \"target_company_id\": 2,\n  \"environment\": \"beta\"\n}"
						},
						"url": {
							"raw": "{{base_url}}/v1/companies/{{company_id}}/gre-credentials/copy",
							"host": ["{{base_url}}"],
							"path": ["v1", "companies", "{{company_id}}", "gre-credentials", "copy"]
						}
					},
					"response": []
				},
				{
					"name": "12.9 - Limpiar Credenciales GRE",
					"request": {
						"method": "DELETE",
						"header": [
							{
								"key": "Authorization",
								"value": "Bearer {{access_token}}"
							},
							{
								"key": "Accept",
								"value": "application/json"
							}
						],
						"url": {
							"raw": "{{base_url}}/v1/companies/{{company_id}}/gre-credentials/clear",
							"host": ["{{base_url}}"],
							"path": ["v1", "companies", "{{company_id}}", "gre-credentials", "clear"]
						}
					},
					"response": []
				},
				{
					"name": "12.10 - Obtener Credenciales GRE por Defecto (BETA)",
					"request": {
						"method": "GET",
						"header": [
							{
								"key": "Authorization",
								"value": "Bearer {{access_token}}"
							},
							{
								"key": "Accept",
								"value": "application/json"
							}
						],
						"url": {
							"raw": "{{base_url}}/v1/gre-credentials/defaults/beta",
							"host": ["{{base_url}}"],
							"path": ["v1", "gre-credentials", "defaults", "beta"]
						}
					},
					"response": []
				}
			]
		},
		{
			"name": "🔍 13. MONITOREO Y ESTADO",
			"item": [
				{
					"name": "13.1 - Estado Actual del Sistema",
					"request": {
						"method": "GET",
						"header": [
							{
								"key": "Accept",
								"value": "application/json"
							}
						],
						"url": {
							"raw": "{{base_url}}/setup/status",
							"host": ["{{base_url}}"],
							"path": ["setup", "status"]
						}
					},
					"response": []
				},
				{
					"name": "13.2 - Información del Usuario Actual",
					"request": {
						"method": "GET",
						"header": [
							{
								"key": "Authorization",
								"value": "Bearer {{access_token}}"
							},
							{
								"key": "Accept",
								"value": "application/json"
							}
						],
						"url": {
							"raw": "{{base_url}}/v1/auth/me",
							"host": ["{{base_url}}"],
							"path": ["v1", "auth", "me"]
						}
					},
					"response": []
				},
				{
					"name": "13.3 - Verificar Todos los Resúmenes Pendientes",
					"request": {
						"method": "POST",
						"header": [
							{
								"key": "Authorization",
								"value": "Bearer {{access_token}}"
							},
							{
								"key": "Content-Type",
								"value": "application/json"
							},
							{
								"key": "Accept",
								"value": "application/json"
							}
						],
						"body": {
							"mode": "raw",
							"raw": "{\n  \"company_id\": {{company_id}}\n}"
						},
						"url": {
							"raw": "{{base_url}}/v1/daily-summaries/check-all-pending",
							"host": ["{{base_url}}"],
							"path": ["v1", "daily-summaries", "check-all-pending"]
						}
					},
					"response": []
				}
			]
		},
		{
			"name": "🚪 14. LOGOUT",
			"item": [
				{
					"name": "14.1 - Cerrar Sesión",
					"event": [
						{
							"listen": "test",
							"script": {
								"type": "text/javascript",
								"exec": [
									"if (pm.response.code === 200) {",
									"    pm.collectionVariables.set('access_token', '');",
									"    console.log('Token limpiado - Sesión cerrada');",
									"}"
								]
							}
						}
					],
					"request": {
						"method": "POST",
						"header": [
							{
								"key": "Authorization",
								"value": "Bearer {{access_token}}"
							},
							{
								"key": "Accept",
								"value": "application/json"
							}
						],
						"url": {
							"raw": "{{base_url}}/v1/auth/logout",
							"host": ["{{base_url}}"],
							"path": ["v1", "auth", "logout"]
						}
					},
					"response": []
				}
			]
		}
	],
	"auth": {
		"type": "bearer",
		"bearer": [
			{
				"key": "token",
				"value": "{{access_token}}",
				"type": "string"
			}
		]
	},
	"variable": [
		{
			"key": "base_url",
			"value": "http://localhost:8000/api",
			"type": "string"
		},
		{
			"key": "access_token",
			"value": "",
			"type": "string"
		},
		{
			"key": "company_id",
			"value": "",
			"type": "string"
		},
		{
			"key": "branch_id",
			"value": "",
			"type": "string"
		},
		{
			"key": "client_id",
			"value": "",
			"type": "string"
		},
		{
			"key": "invoice_id",
			"value": "",
			"type": "string"
		},
		{
			"key": "boleta_id",
			"value": "",
			"type": "string"
		},
		{
			"key": "credit_note_id",
			"value": "",
			"type": "string"
		},
		{
			"key": "debit_note_id",
			"value": "",
			"type": "string"
		},
		{
			"key": "dispatch_guide_id",
			"value": "",
			"type": "string"
		}
	]
}